gameorganiser/build/linuxtest/Analysis-00.toc
gameorganiser/build/linuxtest/EXE-00.toc
gameorganiser/build/linuxtest/PKG-00.toc
gameorganiser/build/linuxtest/PYZ-00.pyz
gameorganiser/build/linuxtest/PYZ-00.toc
gameorganiser/build/linuxtest/base_library.zip
gameorganiser/build/linuxtest/linuxtest.pkg
gameorganiser/build/linuxtest/warn-linuxtest.txt
gameorganiser/build/linuxtest/xref-linuxtest.html
gameorganiser/build/main/Analysis-00.toc
gameorganiser/build/main/EXE-00.toc
gameorganiser/build/main/PKG-00.toc
gameorganiser/build/main/PYZ-00.pyz
gameorganiser/build/main/PYZ-00.toc
gameorganiser/build/main/base_library.zip
gameorganiser/build/main/main.pkg
gameorganiser/build/main/warn-main.txt
gameorganiser/build/main/xref-main.html
gameorganiser/dist/linuxtest
gameorganiser/dist/main
gameorganiser/games.csv
gameorganiser/games.json
gameorganiser/linuxtest.spec
gameorganiser/main.py
gameorganiser/main.spec
gameorganiser-1.3.0.dist-info/LICENSE
gameorganiser-1.3.0.dist-info/METADATA
gameorganiser-1.3.0.dist-info/WHEEL
gameorganiser-1.3.0.dist-info/RECORD
