Metadata-Version: 2.3
Name: gameorganiser
Version: 1.3.0
Summary: A Python application to help organize board and card games by tracking game details and shelf locations.
Author: dragonruler1000
Author-email: github@me.minecraftchest2.us
Requires-Python: >=3.13
Classifier: Programming Language :: Python :: 3
Classifier: Programming Language :: Python :: 3.13
